{
  "datasetId": "conab.operacoes-comercializacao",
  "endpoints": [
    "https://portaldeinformacoes.conab.gov.br/downloads/arquivos/Leilao.txt",
    "https://portaldeinformacoes.conab.gov.br/download-arquivos.html"
  ],
  "consecutiveFailureDays": 0,
  "lastSuccessDate": "2026-06-29",
  "severity": "ok",
  "message": "Official source responded successfully (sample probe).",
  "lastSampleSha256": "1e9452239754319763cf45a954f8803f139719503d078932d2bce1c1c8bdebba",
  "lastModified": "Sun, 28 Jun 2026 11:00:02 GMT"
}
